{
    "pd": {
        "restServiceMessage": {
            "serviceCallFlag": "Y",
            "serviceDataFoundFlag": "Y",
            "serviceDataResultFlag": "Y",
            "serviceInputValidFlag": "Y",
            "serviceMessage": "Data Found !!!"
        },
        "trainServiceProfile": {
            "STA": "09:45",
            "STD": "17:00",
            "classOfTravel": "3E",
            "coachPositionAtSource": [],
            "daysOfRunFromSource": "Mon,Wed,Fri",
            "daysOfRunFromSourceNumeric": "1010100",
            "destination": "YPR",
            "destinationDayCount": 2,
            "destinationName": "YASVANTPUR JN",
            "destinationNameHindi": "यशवंतपुर जं.",
            "destinationPF": "4",
            "futureTrainFlag": 0,
            "gauge": "BG",
            "hashMapStationListWTT": {
                "AEK": 113,
                "AFK": 46,
                "AMY": 8,
                "ANU": 92,
                "AWY": 44,
                "BAND": 118,
                "BLRR": 116,
                "BPHI": 117,
                "CBE": 76,
                "CBF": 77,
                "CGV": 27,
                "CGY": 26,
                "CKI": 50,
                "CNGR": 24,
                "CRLM": 115,
                "CRY": 6,
                "CV": 91,
                "CWR": 45,
                "CYN": 23,
                "DC": 95,
                "DINR": 49,
                "DPJ": 105,
                "ED": 90,
                "ERN": 41,
                "ERSC": 40,
                "ERSD": 39,
                "ETM": 30,
                "ETMD": 73,
                "EVA": 10,
                "HEB": 119,
                "HLE": 114,
                "HSRA": 111,
                "IGR": 87,
                "IGU": 80,
                "IJK": 51,
                "IPL": 42,
                "IRP": 14,
                "KDTY": 32,
                "KFE": 37,
                "KFI": 11,
                "KFQ": 29,
                "KJKD": 71,
                "KLMR": 43,
                "KMLM": 110,
                "KPTM": 35,
                "KPY": 19,
                "KRAN": 48,
                "KRPP": 31,
                "KTKU": 70,
                "KTYM": 28,
                "KUC": 47,
                "KVLR": 101,
                "KVU": 7,
                "KXP": 3,
                "KYJ": 21,
                "KZK": 2,
                "LDY": 66,
                "LOGH": 120,
                "MDKI": 74,
                "MGK": 57,
                "MGSJ": 98,
                "MNKH": 112,
                "MNTT": 36,
                "MNUR": 63,
                "MNY": 67,
                "MPC": 103,
                "MQO": 17,
                "MQU": 4,
                "MUC": 59,
                "MVLK": 22,
                "MVPM": 94,
                "MYY": 13,
                "MZU": 107,
                "NYI": 52,
                "OCR": 20,
                "OLR": 54,
                "OML": 99,
                "OTP": 64,
                "PCV": 106,
                "PGT": 69,
                "PGZ": 5,
                "PLL": 68,
                "PLMD": 78,
                "PLPM": 65,
                "PNQ": 56,
                "PRND": 16,
                "PRNT": 109,
                "PTJ": 75,
                "PUK": 53,
                "PVRD": 34,
                "PVU": 12,
                "PY": 88,
                "QLN": 15,
                "RYC": 108,
                "SA": 97,
                "SGE": 93,
                "SHI": 79,
                "SMDT": 100,
                "SNO": 82,
                "SRRA": 62,
                "SRRB": 61,
                "STKT": 18,
                "SUU": 81,
                "SZV": 104,
                "TCR": 55,
                "TPM": 89,
                "TPP": 102,
                "TRTR": 38,
                "TRVL": 25,
                "TUP": 84,
                "TVCN": 0,
                "UKL": 85,
                "VAK": 9,
                "VARD": 33,
                "VELI": 1,
                "VNJ": 83,
                "VRPD": 96,
                "VTK": 60,
                "VZ": 86,
                "WKI": 58,
                "WRA": 72,
                "YPR": 122,
                "YPRA": 121
            },
            "hashMapStationMultiList": {
                "AWY": "9",
                "BAND": "17",
                "CBE": "12",
                "CGY": "6",
                "CNGR": "4",
                "DPJ": "15",
                "ED": "13",
                "ERN": "8",
                "HSRA": "16",
                "KTYM": "7",
                "KYJ": "2",
                "MVLK": "3",
                "PGT": "11",
                "QLN": "1",
                "SA": "14",
                "TCR": "10",
                "TRVL": "5",
                "TVCN": "0",
                "YPR": "18"
            },
            "heritageTrainFlag": 0,
            "heritageTrainSection": "",
            "idTrainDef": 797096,
            "internationalTrainFlag": 0,
            "mainTrainNo": "",
            "owningRly": "SWR",
            "pantryType": "",
            "prsClassOfTravel": "3E",
            "prsTrainFlag": 1,
            "rakeReversalList": "",
            "reservedTrainFlag": 1,
            "reservedTrainWithGeneralClassFlag": 1,
            "slipMainTrainFlag": 0,
            "slipTrainNo": "",
            "slipType": "",
            "source": "TVCN",
            "sourceName": "",
            "sourceNameHindi": "",
            "sourcePF": "1",
            "totalDistance": 798,
            "trainName": "TVCN YPR GR EXP                               ",
            "trainNameHindi": "कोचुवेलि येस्वन्तपुर गरिबरथ एक्सप्रेस्",
            "trainNo": "12258",
            "trainSubType": "GBR",
            "trainSubTypeName": "GARIB RATH",
            "trainSubTypeNameHindi": "",
            "trainType": "GBR",
            "trainTypeName": "GARIB RATH",
            "trainTypeNameHindi": "गरीब रथ",
            "travelTime": "16:45",
            "utsClassOfTravel": "",
            "utsFareCategory": null,
            "utsFareCategoryDesc": null,
            "utsMstAllowed": 0,
            "utsTrainFlag": 0,
            "vTrainGroup": [
                "GBR",
                "MEXGRP",
                "MEXPAS",
                "PRMGRP",
                "SHOW_IN_NTES",
                "XXX"
            ],
            "vTrainServiceSchedulePTT": [
                {
                    "arrDepDayChangeFlag": 0,
                    "arrPWDCoachPosition": "",
                    "arrivalCoachClass": "",
                    "arrivalCoachPosition": "",
                    "depPWDCoachPosition": "",
                    "departureCoachClass": "ENG-LPR-3E-3E-3E-3E-3E-3E-3E-3E-3E-3E-3E-3E-3E-3E-3E-3E-LPR",
                    "departureCoachPosition": "ENG-GRD-M16-M15-M14-M13-M12-M11-M10-M9-M8-M7-M6-M5-M4-M3-M2-M1-GRD",
                    "distanceFromSource": 0,
                    "division": "TVC",
                    "idTrainDef": 797096,
                    "lattitude": "",
                    "longitude": "",
                    "pfNumber": "",
                    "pttArrivalDayCount": 1,
                    "pttArrivalTimeHHMM": "",
                    "pttArrivalTimeInSecond": 0,
                    "pttDaysOfArrival": "MON,WED,FRI",
                    "pttDaysOfDeparture": "MON,WED,FRI",
                    "pttDepartureDayCount": 1,
                    "pttDepartureTimeHHMM": "17:00",
                    "pttDepartureTimeInSecond": 61200,
                    "pttStopTime": 0,
                    "pttStoppage": 1,
                    "reversalNumber": 0,
                    "samePttStopSeq": 1,
                    "sameStationRepeatSeq": 1,
                    "serialNumber": 1,
                    "srNoWTT": 1,
                    "station": "TVCN",
                    "stationName": "THIRUVANANTHAPURAM NORTH",
                    "stationNameHindi": "तिरुवनंतपुरम उत्तर",
                    "zone": "SR"
                },
                {
                    "arrDepDayChangeFlag": 0,
                    "arrPWDCoachPosition": "",
                    "arrivalCoachClass": "ENG-LPR-3E-3E-3E-3E-3E-3E-3E-3E-3E-3E-3E-3E-3E-3E-3E-3E-LPR",
                    "arrivalCoachPosition": "ENG-GRD-M16-M15-M14-M13-M12-M11-M10-M9-M8-M7-M6-M5-M4-M3-M2-M1-GRD",
                    "depPWDCoachPosition": "",
                    "departureCoachClass": "ENG-LPR-3E-3E-3E-3E-3E-3E-3E-3E-3E-3E-3E-3E-3E-3E-3E-3E-LPR",
                    "departureCoachPosition": "ENG-GRD-M16-M15-M14-M13-M12-M11-M10-M9-M8-M7-M6-M5-M4-M3-M2-M1-GRD",
                    "distanceFromSource": 58,
                    "division": "TVC",
                    "idTrainDef": 797096,
                    "lattitude": "8.886500",
                    "longitude": "76.596700",
                    "pfNumber": "2",
                    "pttArrivalDayCount": 1,
                    "pttArrivalTimeHHMM": "17:50",
                    "pttArrivalTimeInSecond": 64200,
                    "pttDaysOfArrival": "MON,WED,FRI",
                    "pttDaysOfDeparture": "MON,WED,FRI",
                    "pttDepartureDayCount": 1,
                    "pttDepartureTimeHHMM": "17:53",
                    "pttDepartureTimeInSecond": 64380,
                    "pttStopTime": 180,
                    "pttStoppage": 1,
                    "reversalNumber": 0,
                    "samePttStopSeq": 1,
                    "sameStationRepeatSeq": 1,
                    "serialNumber": 2,
                    "srNoWTT": 16,
                    "station": "QLN",
                    "stationName": "KOLLAM JN",
                    "stationNameHindi": "क्विलन जं.",
                    "zone": "SR"
                },
                {
                    "arrDepDayChangeFlag": 0,
                    "arrPWDCoachPosition": "",
                    "arrivalCoachClass": "ENG-LPR-3E-3E-3E-3E-3E-3E-3E-3E-3E-3E-3E-3E-3E-3E-3E-3E-LPR",
                    "arrivalCoachPosition": "ENG-GRD-M16-M15-M14-M13-M12-M11-M10-M9-M8-M7-M6-M5-M4-M3-M2-M1-GRD",
                    "depPWDCoachPosition": "",
                    "departureCoachClass": "ENG-LPR-3E-3E-3E-3E-3E-3E-3E-3E-3E-3E-3E-3E-3E-3E-3E-3E-LPR",
                    "departureCoachPosition": "ENG-GRD-M16-M15-M14-M13-M12-M11-M10-M9-M8-M7-M6-M5-M4-M3-M2-M1-GRD",
                    "distanceFromSource": 99,
                    "division": "TVC",
                    "idTrainDef": 797096,
                    "lattitude": "9.182176",
                    "longitude": "76.512523",
                    "pfNumber": "2",
                    "pttArrivalDayCount": 1,
                    "pttArrivalTimeHHMM": "18:33",
                    "pttArrivalTimeInSecond": 66780,
                    "pttDaysOfArrival": "MON,WED,FRI",
                    "pttDaysOfDeparture": "MON,WED,FRI",
                    "pttDepartureDayCount": 1,
                    "pttDepartureTimeHHMM": "18:35",
                    "pttDepartureTimeInSecond": 66900,
                    "pttStopTime": 120,
                    "pttStoppage": 1,
                    "reversalNumber": 0,
                    "samePttStopSeq": 1,
                    "sameStationRepeatSeq": 1,
                    "serialNumber": 3,
                    "srNoWTT": 22,
                    "station": "KYJ",
                    "stationName": "KAYANKULAM JN",
                    "stationNameHindi": "कायमकुलम जंक्शन",
                    "zone": "SR"
                },
                {
                    "arrDepDayChangeFlag": 0,
                    "arrPWDCoachPosition": "",
                    "arrivalCoachClass": "ENG-LPR-3E-3E-3E-3E-3E-3E-3E-3E-3E-3E-3E-3E-3E-3E-3E-3E-LPR",
                    "arrivalCoachPosition": "ENG-GRD-M16-M15-M14-M13-M12-M11-M10-M9-M8-M7-M6-M5-M4-M3-M2-M1-GRD",
                    "depPWDCoachPosition": "",
                    "departureCoachClass": "ENG-LPR-3E-3E-3E-3E-3E-3E-3E-3E-3E-3E-3E-3E-3E-3E-3E-3E-LPR",
                    "departureCoachPosition": "ENG-GRD-M16-M15-M14-M13-M12-M11-M10-M9-M8-M7-M6-M5-M4-M3-M2-M1-GRD",
                    "distanceFromSource": 107,
                    "division": "TVC",
                    "idTrainDef": 797096,
                    "lattitude": "9.239500",
                    "longitude": "76.545700",
                    "pfNumber": "2",
                    "pttArrivalDayCount": 1,
                    "pttArrivalTimeHHMM": "18:44",
                    "pttArrivalTimeInSecond": 67440,
                    "pttDaysOfArrival": "MON,WED,FRI",
                    "pttDaysOfDeparture": "MON,WED,FRI",
                    "pttDepartureDayCount": 1,
                    "pttDepartureTimeHHMM": "18:45",
                    "pttDepartureTimeInSecond": 67500,
                    "pttStopTime": 60,
                    "pttStoppage": 1,
                    "reversalNumber": 0,
                    "samePttStopSeq": 1,
                    "sameStationRepeatSeq": 1,
                    "serialNumber": 4,
                    "srNoWTT": 23,
                    "station": "MVLK",
                    "stationName": "MAVELIKARA",
                    "stationNameHindi": "मावेलीकारा",
                    "zone": "SR"
                },
                {
                    "arrDepDayChangeFlag": 0,
                    "arrPWDCoachPosition": "",
                    "arrivalCoachClass": "ENG-LPR-3E-3E-3E-3E-3E-3E-3E-3E-3E-3E-3E-3E-3E-3E-3E-3E-LPR",
                    "arrivalCoachPosition": "ENG-GRD-M16-M15-M14-M13-M12-M11-M10-M9-M8-M7-M6-M5-M4-M3-M2-M1-GRD",
                    "depPWDCoachPosition": "",
                    "departureCoachClass": "ENG-LPR-3E-3E-3E-3E-3E-3E-3E-3E-3E-3E-3E-3E-3E-3E-3E-3E-LPR",
                    "departureCoachPosition": "ENG-GRD-M16-M15-M14-M13-M12-M11-M10-M9-M8-M7-M6-M5-M4-M3-M2-M1-GRD",
                    "distanceFromSource": 119,
                    "division": "TVC",
                    "idTrainDef": 797096,
                    "lattitude": "9.319400",
                    "longitude": "76.608100",
                    "pfNumber": "3",
                    "pttArrivalDayCount": 1,
                    "pttArrivalTimeHHMM": "18:55",
                    "pttArrivalTimeInSecond": 68100,
                    "pttDaysOfArrival": "MON,WED,FRI",
                    "pttDaysOfDeparture": "MON,WED,FRI",
                    "pttDepartureDayCount": 1,
                    "pttDepartureTimeHHMM": "18:57",
                    "pttDepartureTimeInSecond": 68220,
                    "pttStopTime": 120,
                    "pttStoppage": 1,
                    "reversalNumber": 0,
                    "samePttStopSeq": 1,
                    "sameStationRepeatSeq": 1,
                    "serialNumber": 5,
                    "srNoWTT": 25,
                    "station": "CNGR",
                    "stationName": "CHENGANNUR",
                    "stationNameHindi": "चेंगन्नूर",
                    "zone": "SR"
                },
                {
                    "arrDepDayChangeFlag": 0,
                    "arrPWDCoachPosition": "",
                    "arrivalCoachClass": "ENG-LPR-3E-3E-3E-3E-3E-3E-3E-3E-3E-3E-3E-3E-3E-3E-3E-3E-LPR",
                    "arrivalCoachPosition": "ENG-GRD-M16-M15-M14-M13-M12-M11-M10-M9-M8-M7-M6-M5-M4-M3-M2-M1-GRD",
                    "depPWDCoachPosition": "",
                    "departureCoachClass": "ENG-LPR-3E-3E-3E-3E-3E-3E-3E-3E-3E-3E-3E-3E-3E-3E-3E-3E-LPR",
                    "departureCoachPosition": "ENG-GRD-M16-M15-M14-M13-M12-M11-M10-M9-M8-M7-M6-M5-M4-M3-M2-M1-GRD",
                    "distanceFromSource": 128,
                    "division": "TVC",
                    "idTrainDef": 797096,
                    "lattitude": "9.391700",
                    "longitude": "76.579800",
                    "pfNumber": "2",
                    "pttArrivalDayCount": 1,
                    "pttArrivalTimeHHMM": "19:06",
                    "pttArrivalTimeInSecond": 68760,
                    "pttDaysOfArrival": "MON,WED,FRI",
                    "pttDaysOfDeparture": "MON,WED,FRI",
                    "pttDepartureDayCount": 1,
                    "pttDepartureTimeHHMM": "19:07",
                    "pttDepartureTimeInSecond": 68820,
                    "pttStopTime": 60,
                    "pttStoppage": 1,
                    "reversalNumber": 0,
                    "samePttStopSeq": 1,
                    "sameStationRepeatSeq": 1,
                    "serialNumber": 6,
                    "srNoWTT": 26,
                    "station": "TRVL",
                    "stationName": "TIRUVALLA",
                    "stationNameHindi": "तिरुवल्ला",
                    "zone": "SR"
                },
                {
                    "arrDepDayChangeFlag": 0,
                    "arrPWDCoachPosition": "",
                    "arrivalCoachClass": "ENG-LPR-3E-3E-3E-3E-3E-3E-3E-3E-3E-3E-3E-3E-3E-3E-3E-3E-LPR",
                    "arrivalCoachPosition": "ENG-GRD-M16-M15-M14-M13-M12-M11-M10-M9-M8-M7-M6-M5-M4-M3-M2-M1-GRD",
                    "depPWDCoachPosition": "",
                    "departureCoachClass": "ENG-LPR-3E-3E-3E-3E-3E-3E-3E-3E-3E-3E-3E-3E-3E-3E-3E-3E-LPR",
                    "departureCoachPosition": "ENG-GRD-M16-M15-M14-M13-M12-M11-M10-M9-M8-M7-M6-M5-M4-M3-M2-M1-GRD",
                    "distanceFromSource": 136,
                    "division": "TVC",
                    "idTrainDef": 797096,
                    "lattitude": "9.449781",
                    "longitude": "76.548314",
                    "pfNumber": "2",
                    "pttArrivalDayCount": 1,
                    "pttArrivalTimeHHMM": "19:16",
                    "pttArrivalTimeInSecond": 69360,
                    "pttDaysOfArrival": "MON,WED,FRI",
                    "pttDaysOfDeparture": "MON,WED,FRI",
                    "pttDepartureDayCount": 1,
                    "pttDepartureTimeHHMM": "19:17",
                    "pttDepartureTimeInSecond": 69420,
                    "pttStopTime": 60,
                    "pttStoppage": 1,
                    "reversalNumber": 0,
                    "samePttStopSeq": 1,
                    "sameStationRepeatSeq": 1,
                    "serialNumber": 7,
                    "srNoWTT": 27,
                    "station": "CGY",
                    "stationName": "CHANGANASSERI",
                    "stationNameHindi": "चन्गनाशेरी",
                    "zone": "SR"
                },
                {
                    "arrDepDayChangeFlag": 0,
                    "arrPWDCoachPosition": "",
                    "arrivalCoachClass": "ENG-LPR-3E-3E-3E-3E-3E-3E-3E-3E-3E-3E-3E-3E-3E-3E-3E-3E-LPR",
                    "arrivalCoachPosition": "ENG-GRD-M16-M15-M14-M13-M12-M11-M10-M9-M8-M7-M6-M5-M4-M3-M2-M1-GRD",
                    "depPWDCoachPosition": "",
                    "departureCoachClass": "ENG-LPR-3E-3E-3E-3E-3E-3E-3E-3E-3E-3E-3E-3E-3E-3E-3E-3E-LPR",
                    "departureCoachPosition": "ENG-GRD-M16-M15-M14-M13-M12-M11-M10-M9-M8-M7-M6-M5-M4-M3-M2-M1-GRD",
                    "distanceFromSource": 154,
                    "division": "TVC",
                    "idTrainDef": 797096,
                    "lattitude": "9.594487",
                    "longitude": "76.532478",
                    "pfNumber": "1",
                    "pttArrivalDayCount": 1,
                    "pttArrivalTimeHHMM": "19:42",
                    "pttArrivalTimeInSecond": 70920,
                    "pttDaysOfArrival": "MON,WED,FRI",
                    "pttDaysOfDeparture": "MON,WED,FRI",
                    "pttDepartureDayCount": 1,
                    "pttDepartureTimeHHMM": "19:45",
                    "pttDepartureTimeInSecond": 71100,
                    "pttStopTime": 180,
                    "pttStoppage": 1,
                    "reversalNumber": 0,
                    "samePttStopSeq": 1,
                    "sameStationRepeatSeq": 1,
                    "serialNumber": 8,
                    "srNoWTT": 29,
                    "station": "KTYM",
                    "stationName": "KOTTAYAM",
                    "stationNameHindi": "कोट्टायम",
                    "zone": "SR"
                },
                {
                    "arrDepDayChangeFlag": 0,
                    "arrPWDCoachPosition": "",
                    "arrivalCoachClass": "ENG-LPR-3E-3E-3E-3E-3E-3E-3E-3E-3E-3E-3E-3E-3E-3E-3E-3E-LPR",
                    "arrivalCoachPosition": "ENG-GRD-M16-M15-M14-M13-M12-M11-M10-M9-M8-M7-M6-M5-M4-M3-M2-M1-GRD",
                    "depPWDCoachPosition": "",
                    "departureCoachClass": "ENG-LPR-3E-3E-3E-3E-3E-3E-3E-3E-3E-3E-3E-3E-3E-3E-3E-3E-LPR",
                    "departureCoachPosition": "ENG-GRD-M16-M15-M14-M13-M12-M11-M10-M9-M8-M7-M6-M5-M4-M3-M2-M1-GRD",
                    "distanceFromSource": 214,
                    "division": "TVC",
                    "idTrainDef": 797096,
                    "lattitude": "9.992012",
                    "longitude": "76.286530",
                    "pfNumber": "1",
                    "pttArrivalDayCount": 1,
                    "pttArrivalTimeHHMM": "20:55",
                    "pttArrivalTimeInSecond": 75300,
                    "pttDaysOfArrival": "MON,WED,FRI",
                    "pttDaysOfDeparture": "MON,WED,FRI",
                    "pttDepartureDayCount": 1,
                    "pttDepartureTimeHHMM": "21:00",
                    "pttDepartureTimeInSecond": 75600,
                    "pttStopTime": 300,
                    "pttStoppage": 1,
                    "reversalNumber": 0,
                    "samePttStopSeq": 1,
                    "sameStationRepeatSeq": 1,
                    "serialNumber": 9,
                    "srNoWTT": 42,
                    "station": "ERN",
                    "stationName": "ERNAKULAM TOWN",
                    "stationNameHindi": "एर्णाकुलम टाउन",
                    "zone": "SR"
                },
                {
                    "arrDepDayChangeFlag": 0,
                    "arrPWDCoachPosition": "",
                    "arrivalCoachClass": "ENG-LPR-3E-3E-3E-3E-3E-3E-3E-3E-3E-3E-3E-3E-3E-3E-3E-3E-LPR",
                    "arrivalCoachPosition": "ENG-GRD-M16-M15-M14-M13-M12-M11-M10-M9-M8-M7-M6-M5-M4-M3-M2-M1-GRD",
                    "depPWDCoachPosition": "",
                    "departureCoachClass": "ENG-LPR-3E-3E-3E-3E-3E-3E-3E-3E-3E-3E-3E-3E-3E-3E-3E-3E-LPR",
                    "departureCoachPosition": "ENG-GRD-M16-M15-M14-M13-M12-M11-M10-M9-M8-M7-M6-M5-M4-M3-M2-M1-GRD",
                    "distanceFromSource": 231,
                    "division": "TVC",
                    "idTrainDef": 797096,
                    "lattitude": "10.107900",
                    "longitude": "76.356200",
                    "pfNumber": "3",
                    "pttArrivalDayCount": 1,
                    "pttArrivalTimeHHMM": "21:22",
                    "pttArrivalTimeInSecond": 76920,
                    "pttDaysOfArrival": "MON,WED,FRI",
                    "pttDaysOfDeparture": "MON,WED,FRI",
                    "pttDepartureDayCount": 1,
                    "pttDepartureTimeHHMM": "21:24",
                    "pttDepartureTimeInSecond": 77040,
                    "pttStopTime": 120,
                    "pttStoppage": 1,
                    "reversalNumber": 0,
                    "samePttStopSeq": 1,
                    "sameStationRepeatSeq": 1,
                    "serialNumber": 10,
                    "srNoWTT": 45,
                    "station": "AWY",
                    "stationName": "ALUVA",
                    "stationNameHindi": "आल्वेन",
                    "zone": "SR"
                },
                {
                    "arrDepDayChangeFlag": 0,
                    "arrPWDCoachPosition": "",
                    "arrivalCoachClass": "ENG-LPR-3E-3E-3E-3E-3E-3E-3E-3E-3E-3E-3E-3E-3E-3E-3E-3E-LPR",
                    "arrivalCoachPosition": "ENG-GRD-M16-M15-M14-M13-M12-M11-M10-M9-M8-M7-M6-M5-M4-M3-M2-M1-GRD",
                    "depPWDCoachPosition": "",
                    "departureCoachClass": "ENG-LPR-3E-3E-3E-3E-3E-3E-3E-3E-3E-3E-3E-3E-3E-3E-3E-3E-LPR",
                    "departureCoachPosition": "ENG-GRD-M16-M15-M14-M13-M12-M11-M10-M9-M8-M7-M6-M5-M4-M3-M2-M1-GRD",
                    "distanceFromSource": 285,
                    "division": "TVC",
                    "idTrainDef": 797096,
                    "lattitude": "10.514480",
                    "longitude": "76.207609",
                    "pfNumber": "2",
                    "pttArrivalDayCount": 1,
                    "pttArrivalTimeHHMM": "22:13",
                    "pttArrivalTimeInSecond": 79980,
                    "pttDaysOfArrival": "MON,WED,FRI",
                    "pttDaysOfDeparture": "MON,WED,FRI",
                    "pttDepartureDayCount": 1,
                    "pttDepartureTimeHHMM": "22:16",
                    "pttDepartureTimeInSecond": 80160,
                    "pttStopTime": 180,
                    "pttStoppage": 1,
                    "reversalNumber": 0,
                    "samePttStopSeq": 1,
                    "sameStationRepeatSeq": 1,
                    "serialNumber": 11,
                    "srNoWTT": 56,
                    "station": "TCR",
                    "stationName": "THRISUR",
                    "stationNameHindi": "त्रिचूर",
                    "zone": "SR"
                },
                {
                    "arrDepDayChangeFlag": 0,
                    "arrPWDCoachPosition": "",
                    "arrivalCoachClass": "ENG-LPR-3E-3E-3E-3E-3E-3E-3E-3E-3E-3E-3E-3E-3E-3E-3E-3E-LPR",
                    "arrivalCoachPosition": "ENG-GRD-M16-M15-M14-M13-M12-M11-M10-M9-M8-M7-M6-M5-M4-M3-M2-M1-GRD",
                    "depPWDCoachPosition": "",
                    "departureCoachClass": "ENG-LPR-3E-3E-3E-3E-3E-3E-3E-3E-3E-3E-3E-3E-3E-3E-3E-3E-LPR",
                    "departureCoachPosition": "ENG-GRD-M16-M15-M14-M13-M12-M11-M10-M9-M8-M7-M6-M5-M4-M3-M2-M1-GRD",
                    "distanceFromSource": 362,
                    "division": "PGT",
                    "idTrainDef": 797096,
                    "lattitude": "10.801691",
                    "longitude": "76.641526",
                    "pfNumber": "5",
                    "pttArrivalDayCount": 2,
                    "pttArrivalTimeHHMM": "00:07",
                    "pttArrivalTimeInSecond": 86820,
                    "pttDaysOfArrival": "TUE,THU,SAT",
                    "pttDaysOfDeparture": "TUE,THU,SAT",
                    "pttDepartureDayCount": 2,
                    "pttDepartureTimeHHMM": "00:10",
                    "pttDepartureTimeInSecond": 87000,
                    "pttStopTime": 180,
                    "pttStoppage": 1,
                    "reversalNumber": 0,
                    "samePttStopSeq": 1,
                    "sameStationRepeatSeq": 1,
                    "serialNumber": 12,
                    "srNoWTT": 70,
                    "station": "PGT",
                    "stationName": "PALAKKAD JN",
                    "stationNameHindi": "पालक्काड जंक्शन",
                    "zone": "SR"
                },
                {
                    "arrDepDayChangeFlag": 0,
                    "arrPWDCoachPosition": "",
                    "arrivalCoachClass": "ENG-LPR-3E-3E-3E-3E-3E-3E-3E-3E-3E-3E-3E-3E-3E-3E-3E-3E-LPR",
                    "arrivalCoachPosition": "ENG-GRD-M16-M15-M14-M13-M12-M11-M10-M9-M8-M7-M6-M5-M4-M3-M2-M1-GRD",
                    "depPWDCoachPosition": "",
                    "departureCoachClass": "ENG-LPR-3E-3E-3E-3E-3E-3E-3E-3E-3E-3E-3E-3E-3E-3E-3E-3E-LPR",
                    "departureCoachPosition": "ENG-GRD-M16-M15-M14-M13-M12-M11-M10-M9-M8-M7-M6-M5-M4-M3-M2-M1-GRD",
                    "distanceFromSource": 417,
                    "division": "SA",
                    "idTrainDef": 797096,
                    "lattitude": "10.997479",
                    "longitude": "76.966138",
                    "pfNumber": "3",
                    "pttArrivalDayCount": 2,
                    "pttArrivalTimeHHMM": "01:32",
                    "pttArrivalTimeInSecond": 91920,
                    "pttDaysOfArrival": "TUE,THU,SAT",
                    "pttDaysOfDeparture": "TUE,THU,SAT",
                    "pttDepartureDayCount": 2,
                    "pttDepartureTimeHHMM": "01:35",
                    "pttDepartureTimeInSecond": 92100,
                    "pttStopTime": 180,
                    "pttStoppage": 1,
                    "reversalNumber": 0,
                    "samePttStopSeq": 1,
                    "sameStationRepeatSeq": 1,
                    "serialNumber": 13,
                    "srNoWTT": 77,
                    "station": "CBE",
                    "stationName": "COIMBATORE JN",
                    "stationNameHindi": "कोयंबटूर जं.",
                    "zone": "SR"
                },
                {
                    "arrDepDayChangeFlag": 0,
                    "arrPWDCoachPosition": "",
                    "arrivalCoachClass": "ENG-LPR-3E-3E-3E-3E-3E-3E-3E-3E-3E-3E-3E-3E-3E-3E-3E-3E-LPR",
                    "arrivalCoachPosition": "ENG-GRD-M16-M15-M14-M13-M12-M11-M10-M9-M8-M7-M6-M5-M4-M3-M2-M1-GRD",
                    "depPWDCoachPosition": "",
                    "departureCoachClass": "ENG-LPR-3E-3E-3E-3E-3E-3E-3E-3E-3E-3E-3E-3E-3E-3E-3E-3E-LPR",
                    "departureCoachPosition": "ENG-GRD-M16-M15-M14-M13-M12-M11-M10-M9-M8-M7-M6-M5-M4-M3-M2-M1-GRD",
                    "distanceFromSource": 517,
                    "division": "SA",
                    "idTrainDef": 797096,
                    "lattitude": "11.327400",
                    "longitude": "77.725600",
                    "pfNumber": "1",
                    "pttArrivalDayCount": 2,
                    "pttArrivalTimeHHMM": "03:10",
                    "pttArrivalTimeInSecond": 97800,
                    "pttDaysOfArrival": "TUE,THU,SAT",
                    "pttDaysOfDeparture": "TUE,THU,SAT",
                    "pttDepartureDayCount": 2,
                    "pttDepartureTimeHHMM": "03:15",
                    "pttDepartureTimeInSecond": 98100,
                    "pttStopTime": 300,
                    "pttStoppage": 1,
                    "reversalNumber": 0,
                    "samePttStopSeq": 1,
                    "sameStationRepeatSeq": 1,
                    "serialNumber": 14,
                    "srNoWTT": 91,
                    "station": "ED",
                    "stationName": "ERODE JN",
                    "stationNameHindi": "इरोड जं.",
                    "zone": "SR"
                },
                {
                    "arrDepDayChangeFlag": 0,
                    "arrPWDCoachPosition": "",
                    "arrivalCoachClass": "ENG-LPR-3E-3E-3E-3E-3E-3E-3E-3E-3E-3E-3E-3E-3E-3E-3E-3E-LPR",
                    "arrivalCoachPosition": "ENG-GRD-M16-M15-M14-M13-M12-M11-M10-M9-M8-M7-M6-M5-M4-M3-M2-M1-GRD",
                    "depPWDCoachPosition": "",
                    "departureCoachClass": "ENG-LPR-3E-3E-3E-3E-3E-3E-3E-3E-3E-3E-3E-3E-3E-3E-3E-3E-LPR",
                    "departureCoachPosition": "ENG-GRD-M16-M15-M14-M13-M12-M11-M10-M9-M8-M7-M6-M5-M4-M3-M2-M1-GRD",
                    "distanceFromSource": 577,
                    "division": "SA",
                    "idTrainDef": 797096,
                    "lattitude": "11.671276",
                    "longitude": "78.112965",
                    "pfNumber": "5",
                    "pttArrivalDayCount": 2,
                    "pttArrivalTimeHHMM": "04:07",
                    "pttArrivalTimeInSecond": 101220,
                    "pttDaysOfArrival": "TUE,THU,SAT",
                    "pttDaysOfDeparture": "TUE,THU,SAT",
                    "pttDepartureDayCount": 2,
                    "pttDepartureTimeHHMM": "04:10",
                    "pttDepartureTimeInSecond": 101400,
                    "pttStopTime": 180,
                    "pttStoppage": 1,
                    "reversalNumber": 0,
                    "samePttStopSeq": 1,
                    "sameStationRepeatSeq": 1,
                    "serialNumber": 15,
                    "srNoWTT": 98,
                    "station": "SA",
                    "stationName": "SALEM JN",
                    "stationNameHindi": "सेलम जं.",
                    "zone": "SR"
                },
                {
                    "arrDepDayChangeFlag": 0,
                    "arrPWDCoachPosition": "",
                    "arrivalCoachClass": "ENG-LPR-3E-3E-3E-3E-3E-3E-3E-3E-3E-3E-3E-3E-3E-3E-3E-3E-LPR",
                    "arrivalCoachPosition": "ENG-GRD-M16-M15-M14-M13-M12-M11-M10-M9-M8-M7-M6-M5-M4-M3-M2-M1-GRD",
                    "depPWDCoachPosition": "",
                    "departureCoachClass": "ENG-LPR-3E-3E-3E-3E-3E-3E-3E-3E-3E-3E-3E-3E-3E-3E-3E-3E-LPR",
                    "departureCoachPosition": "ENG-GRD-M16-M15-M14-M13-M12-M11-M10-M9-M8-M7-M6-M5-M4-M3-M2-M1-GRD",
                    "distanceFromSource": 644,
                    "division": "SBC",
                    "idTrainDef": 797096,
                    "lattitude": "12.126100",
                    "longitude": "78.154200",
                    "pfNumber": "3",
                    "pttArrivalDayCount": 2,
                    "pttArrivalTimeHHMM": "05:43",
                    "pttArrivalTimeInSecond": 106980,
                    "pttDaysOfArrival": "TUE,THU,SAT",
                    "pttDaysOfDeparture": "TUE,THU,SAT",
                    "pttDepartureDayCount": 2,
                    "pttDepartureTimeHHMM": "05:45",
                    "pttDepartureTimeInSecond": 107100,
                    "pttStopTime": 120,
                    "pttStoppage": 1,
                    "reversalNumber": 0,
                    "samePttStopSeq": 1,
                    "sameStationRepeatSeq": 1,
                    "serialNumber": 16,
                    "srNoWTT": 106,
                    "station": "DPJ",
                    "stationName": "DHARMAPURI",
                    "stationNameHindi": "धर्मापुरी",
                    "zone": "SWR"
                },
                {
                    "arrDepDayChangeFlag": 0,
                    "arrPWDCoachPosition": "",
                    "arrivalCoachClass": "ENG-LPR-3E-3E-3E-3E-3E-3E-3E-3E-3E-3E-3E-3E-3E-3E-3E-3E-LPR",
                    "arrivalCoachPosition": "ENG-GRD-M16-M15-M14-M13-M12-M11-M10-M9-M8-M7-M6-M5-M4-M3-M2-M1-GRD",
                    "depPWDCoachPosition": "",
                    "departureCoachClass": "ENG-LPR-3E-3E-3E-3E-3E-3E-3E-3E-3E-3E-3E-3E-3E-3E-3E-3E-LPR",
                    "departureCoachPosition": "ENG-GRD-M16-M15-M14-M13-M12-M11-M10-M9-M8-M7-M6-M5-M4-M3-M2-M1-GRD",
                    "distanceFromSource": 736,
                    "division": "SBC",
                    "idTrainDef": 797096,
                    "lattitude": "12.717700",
                    "longitude": "77.823000",
                    "pfNumber": "2",
                    "pttArrivalDayCount": 2,
                    "pttArrivalTimeHHMM": "07:13",
                    "pttArrivalTimeInSecond": 112380,
                    "pttDaysOfArrival": "TUE,THU,SAT",
                    "pttDaysOfDeparture": "TUE,THU,SAT",
                    "pttDepartureDayCount": 2,
                    "pttDepartureTimeHHMM": "07:15",
                    "pttDepartureTimeInSecond": 112500,
                    "pttStopTime": 120,
                    "pttStoppage": 1,
                    "reversalNumber": 0,
                    "samePttStopSeq": 1,
                    "sameStationRepeatSeq": 1,
                    "serialNumber": 17,
                    "srNoWTT": 112,
                    "station": "HSRA",
                    "stationName": "HOSUR",
                    "stationNameHindi": "होसपुर",
                    "zone": "SWR"
                },
                {
                    "arrDepDayChangeFlag": 0,
                    "arrPWDCoachPosition": "",
                    "arrivalCoachClass": "ENG-LPR-3E-3E-3E-3E-3E-3E-3E-3E-3E-3E-3E-3E-3E-3E-3E-3E-LPR",
                    "arrivalCoachPosition": "ENG-GRD-M16-M15-M14-M13-M12-M11-M10-M9-M8-M7-M6-M5-M4-M3-M2-M1-GRD",
                    "depPWDCoachPosition": "",
                    "departureCoachClass": "ENG-LPR-3E-3E-3E-3E-3E-3E-3E-3E-3E-3E-3E-3E-3E-3E-3E-3E-LPR",
                    "departureCoachPosition": "ENG-GRD-M16-M15-M14-M13-M12-M11-M10-M9-M8-M7-M6-M5-M4-M3-M2-M1-GRD",
                    "distanceFromSource": 786,
                    "division": "SBC",
                    "idTrainDef": 797096,
                    "lattitude": "13.005770",
                    "longitude": "77.628236",
                    "pfNumber": "2",
                    "pttArrivalDayCount": 2,
                    "pttArrivalTimeHHMM": "08:28",
                    "pttArrivalTimeInSecond": 116880,
                    "pttDaysOfArrival": "TUE,THU,SAT",
                    "pttDaysOfDeparture": "TUE,THU,SAT",
                    "pttDepartureDayCount": 2,
                    "pttDepartureTimeHHMM": "08:30",
                    "pttDepartureTimeInSecond": 117000,
                    "pttStopTime": 120,
                    "pttStoppage": 1,
                    "reversalNumber": 0,
                    "samePttStopSeq": 1,
                    "sameStationRepeatSeq": 1,
                    "serialNumber": 18,
                    "srNoWTT": 119,
                    "station": "BAND",
                    "stationName": "BANASWADI",
                    "stationNameHindi": "बनासवाड़ी",
                    "zone": "SWR"
                },
                {
                    "arrDepDayChangeFlag": 0,
                    "arrPWDCoachPosition": "",
                    "arrivalCoachClass": "ENG-LPR-3E-3E-3E-3E-3E-3E-3E-3E-3E-3E-3E-3E-3E-3E-3E-3E-LPR",
                    "arrivalCoachPosition": "ENG-GRD-M16-M15-M14-M13-M12-M11-M10-M9-M8-M7-M6-M5-M4-M3-M2-M1-GRD",
                    "depPWDCoachPosition": "",
                    "departureCoachClass": "",
                    "departureCoachPosition": "",
                    "distanceFromSource": 799,
                    "division": "SBC",
                    "idTrainDef": 797096,
                    "lattitude": "13.023039",
                    "longitude": "77.551374",
                    "pfNumber": "4",
                    "pttArrivalDayCount": 2,
                    "pttArrivalTimeHHMM": "09:45",
                    "pttArrivalTimeInSecond": 121500,
                    "pttDaysOfArrival": "TUE,THU,SAT",
                    "pttDaysOfDeparture": "TUE,THU,SAT",
                    "pttDepartureDayCount": 2,
                    "pttDepartureTimeHHMM": "",
                    "pttDepartureTimeInSecond": 0,
                    "pttStopTime": 0,
                    "pttStoppage": 1,
                    "reversalNumber": 0,
                    "samePttStopSeq": 1,
                    "sameStationRepeatSeq": 1,
                    "serialNumber": 19,
                    "srNoWTT": 123,
                    "station": "YPR",
                    "stationName": "YESVANTPUR JN.",
                    "stationNameHindi": "यशवंतपुर जं.",
                    "zone": "SWR"
                }
            ],
            "vTrainServiceScheduleWTT": [
                {
                    "lattitude": "",
                    "longitude": "",
                    "serialNumber": 1,
                    "station": "TVCN"
                },
                {
                    "lattitude": "8.531100",
                    "longitude": "76.880500",
                    "serialNumber": 2,
                    "station": "VELI"
                },
                {
                    "lattitude": "8.556200",
                    "longitude": "76.872600",
                    "serialNumber": 3,
                    "station": "KZK"
                },
                {
                    "lattitude": "8.587302",
                    "longitude": "76.854172",
                    "serialNumber": 4,
                    "station": "KXP"
                },
                {
                    "lattitude": "8.613600",
                    "longitude": "76.830200",
                    "serialNumber": 5,
                    "station": "MQU"
                },
                {
                    "lattitude": "8.631431",
                    "longitude": "76.808081",
                    "serialNumber": 6,
                    "station": "PGZ"
                },
                {
                    "lattitude": "8.658778",
                    "longitude": "76.785810",
                    "serialNumber": 7,
                    "station": "CRY"
                },
                {
                    "lattitude": "8.679200",
                    "longitude": "76.766800",
                    "serialNumber": 8,
                    "station": "KVU"
                },
                {
                    "lattitude": "8.700160",
                    "longitude": "76.758642",
                    "serialNumber": 9,
                    "station": "AMY"
                },
                {
                    "lattitude": "8.740800",
                    "longitude": "76.723000",
                    "serialNumber": 10,
                    "station": "VAK"
                },
                {
                    "lattitude": "8.763023",
                    "longitude": "76.697617",
                    "serialNumber": 11,
                    "station": "EVA"
                },
                {
                    "lattitude": "8.779225",
                    "longitude": "76.679420",
                    "serialNumber": 12,
                    "station": "KFI"
                },
                {
                    "lattitude": "8.815800",
                    "longitude": "76.668300",
                    "serialNumber": 13,
                    "station": "PVU"
                },
                {
                    "lattitude": "8.837900",
                    "longitude": "76.647400",
                    "serialNumber": 14,
                    "station": "MYY"
                },
                {
                    "lattitude": "8.867348",
                    "longitude": "76.623459",
                    "serialNumber": 15,
                    "station": "IRP"
                },
                {
                    "lattitude": "8.886500",
                    "longitude": "76.596700",
                    "serialNumber": 16,
                    "station": "QLN"
                },
                {
                    "lattitude": "8.948100",
                    "longitude": "76.620500",
                    "serialNumber": 17,
                    "station": "PRND"
                },
                {
                    "lattitude": "8.997203",
                    "longitude": "76.610456",
                    "serialNumber": 18,
                    "station": "MQO"
                },
                {
                    "lattitude": "9.031200",
                    "longitude": "76.600800",
                    "serialNumber": 19,
                    "station": "STKT"
                },
                {
                    "lattitude": "9.065568",
                    "longitude": "76.544323",
                    "serialNumber": 20,
                    "station": "KPY"
                },
                {
                    "lattitude": "9.131600",
                    "longitude": "76.525200",
                    "serialNumber": 21,
                    "station": "OCR"
                },
                {
                    "lattitude": "9.182176",
                    "longitude": "76.512523",
                    "serialNumber": 22,
                    "station": "KYJ"
                },
                {
                    "lattitude": "9.239500",
                    "longitude": "76.545700",
                    "serialNumber": 23,
                    "station": "MVLK"
                },
                {
                    "lattitude": "9.273039",
                    "longitude": "76.585007",
                    "serialNumber": 24,
                    "station": "CYN"
                },
                {
                    "lattitude": "9.319400",
                    "longitude": "76.608100",
                    "serialNumber": 25,
                    "station": "CNGR"
                },
                {
                    "lattitude": "9.391700",
                    "longitude": "76.579800",
                    "serialNumber": 26,
                    "station": "TRVL"
                },
                {
                    "lattitude": "9.449781",
                    "longitude": "76.548314",
                    "serialNumber": 27,
                    "station": "CGY"
                },
                {
                    "lattitude": "9.537500",
                    "longitude": "76.525600",
                    "serialNumber": 28,
                    "station": "CGV"
                },
                {
                    "lattitude": "9.594487",
                    "longitude": "76.532478",
                    "serialNumber": 29,
                    "station": "KTYM"
                },
                {
                    "lattitude": "9.617506",
                    "longitude": "76.532049",
                    "serialNumber": 30,
                    "station": "KFQ"
                },
                {
                    "lattitude": "9.676500",
                    "longitude": "76.545400",
                    "serialNumber": 31,
                    "station": "ETM"
                },
                {
                    "lattitude": "9.734775",
                    "longitude": "76.510849",
                    "serialNumber": 32,
                    "station": "KRPP"
                },
                {
                    "lattitude": "9.755838",
                    "longitude": "76.492310",
                    "serialNumber": 33,
                    "station": "KDTY"
                },
                {
                    "lattitude": "9.777408",
                    "longitude": "76.474371",
                    "serialNumber": 34,
                    "station": "VARD"
                },
                {
                    "lattitude": "9.829100",
                    "longitude": "76.455200",
                    "serialNumber": 35,
                    "station": "PVRD"
                },
                {
                    "lattitude": "9.861981",
                    "longitude": "76.410599",
                    "serialNumber": 36,
                    "station": "KPTM"
                },
                {
                    "lattitude": "9.901200",
                    "longitude": "76.389300",
                    "serialNumber": 37,
                    "station": "MNTT"
                },
                {
                    "lattitude": "9.923537",
                    "longitude": "76.376610",
                    "serialNumber": 38,
                    "station": "KFE"
                },
                {
                    "lattitude": "9.949830",
                    "longitude": "76.352491",
                    "serialNumber": 39,
                    "station": "TRTR"
                },
                {
                    "lattitude": "9.980052",
                    "longitude": "76.306889",
                    "serialNumber": 40,
                    "station": "ERSD"
                },
                {
                    "lattitude": "9.977980",
                    "longitude": "76.289779",
                    "serialNumber": 41,
                    "station": "ERSC"
                },
                {
                    "lattitude": "9.992012",
                    "longitude": "76.286530",
                    "serialNumber": 42,
                    "station": "ERN"
                },
                {
                    "lattitude": "10.034528",
                    "longitude": "76.298461",
                    "serialNumber": 43,
                    "station": "IPL"
                },
                {
                    "lattitude": "10.062200",
                    "longitude": "76.327300",
                    "serialNumber": 44,
                    "station": "KLMR"
                },
                {
                    "lattitude": "10.107900",
                    "longitude": "76.356200",
                    "serialNumber": 45,
                    "station": "AWY"
                },
                {
                    "lattitude": "10.132764",
                    "longitude": "76.371889",
                    "serialNumber": 46,
                    "station": "CWR"
                },
                {
                    "lattitude": "10.183400",
                    "longitude": "76.377600",
                    "serialNumber": 47,
                    "station": "AFK"
                },
                {
                    "lattitude": "10.226100",
                    "longitude": "76.373400",
                    "serialNumber": 48,
                    "station": "KUC"
                },
                {
                    "lattitude": "10.260533",
                    "longitude": "76.356311",
                    "serialNumber": 49,
                    "station": "KRAN"
                },
                {
                    "lattitude": "10.287474",
                    "longitude": "76.335969",
                    "serialNumber": 50,
                    "station": "DINR"
                },
                {
                    "lattitude": "10.301900",
                    "longitude": "76.321900",
                    "serialNumber": 51,
                    "station": "CKI"
                },
                {
                    "lattitude": "10.339900",
                    "longitude": "76.281400",
                    "serialNumber": 52,
                    "station": "IJK"
                },
                {
                    "lattitude": "10.391965",
                    "longitude": "76.275544",
                    "serialNumber": 53,
                    "station": "NYI"
                },
                {
                    "lattitude": "10.420600",
                    "longitude": "76.260800",
                    "serialNumber": 54,
                    "station": "PUK"
                },
                {
                    "lattitude": "10.473400",
                    "longitude": "76.237200",
                    "serialNumber": 55,
                    "station": "OLR"
                },
                {
                    "lattitude": "10.514480",
                    "longitude": "76.207609",
                    "serialNumber": 56,
                    "station": "TCR"
                },
                {
                    "lattitude": "10.534500",
                    "longitude": "76.208900",
                    "serialNumber": 57,
                    "station": "PNQ"
                },
                {
                    "lattitude": "10.597339",
                    "longitude": "76.208209",
                    "serialNumber": 58,
                    "station": "MGK"
                },
                {
                    "lattitude": "10.649100",
                    "longitude": "76.237200",
                    "serialNumber": 59,
                    "station": "WKI"
                },
                {
                    "lattitude": "10.706153",
                    "longitude": "76.271725",
                    "serialNumber": 60,
                    "station": "MUC"
                },
                {
                    "lattitude": "10.731453",
                    "longitude": "76.280823",
                    "serialNumber": 61,
                    "station": "VTK"
                },
                {
                    "lattitude": "10.759418",
                    "longitude": "76.270550",
                    "serialNumber": 62,
                    "station": "SRRB"
                },
                {
                    "lattitude": "10.759112",
                    "longitude": "76.281497",
                    "serialNumber": 63,
                    "station": "SRRA"
                },
                {
                    "lattitude": "10.749100",
                    "longitude": "76.323300",
                    "serialNumber": 64,
                    "station": "MNUR"
                },
                {
                    "lattitude": "10.769700",
                    "longitude": "76.377600",
                    "serialNumber": 65,
                    "station": "OTP"
                },
                {
                    "lattitude": "10.750800",
                    "longitude": "76.405800",
                    "serialNumber": 66,
                    "station": "PLPM"
                },
                {
                    "lattitude": "10.753100",
                    "longitude": "76.434400",
                    "serialNumber": 67,
                    "station": "LDY"
                },
                {
                    "lattitude": "10.771800",
                    "longitude": "76.500500",
                    "serialNumber": 68,
                    "station": "MNY"
                },
                {
                    "lattitude": "10.800500",
                    "longitude": "76.559600",
                    "serialNumber": 69,
                    "station": "PLL"
                },
                {
                    "lattitude": "10.801691",
                    "longitude": "76.641526",
                    "serialNumber": 70,
                    "station": "PGT"
                },
                {
                    "lattitude": "10.815700",
                    "longitude": "76.693400",
                    "serialNumber": 71,
                    "station": "KTKU"
                },
                {
                    "lattitude": "10.800400",
                    "longitude": "76.754800",
                    "serialNumber": 72,
                    "station": "KJKD"
                },
                {
                    "lattitude": "10.845000",
                    "longitude": "76.837600",
                    "serialNumber": 73,
                    "station": "WRA"
                },
                {
                    "lattitude": "10.898500",
                    "longitude": "76.896900",
                    "serialNumber": 74,
                    "station": "ETMD"
                },
                {
                    "lattitude": "10.900500",
                    "longitude": "76.942600",
                    "serialNumber": 75,
                    "station": "MDKI"
                },
                {
                    "lattitude": "10.964900",
                    "longitude": "76.989600",
                    "serialNumber": 76,
                    "station": "PTJ"
                },
                {
                    "lattitude": "10.997479",
                    "longitude": "76.966138",
                    "serialNumber": 77,
                    "station": "CBE"
                },
                {
                    "lattitude": "11.020227",
                    "longitude": "76.954594",
                    "serialNumber": 78,
                    "station": "CBF"
                },
                {
                    "lattitude": "11.033200",
                    "longitude": "76.999500",
                    "serialNumber": 79,
                    "station": "PLMD"
                },
                {
                    "lattitude": "11.012700",
                    "longitude": "77.039300",
                    "serialNumber": 80,
                    "station": "SHI"
                },
                {
                    "lattitude": "11.016800",
                    "longitude": "77.068800",
                    "serialNumber": 81,
                    "station": "IGU"
                },
                {
                    "lattitude": "11.049500",
                    "longitude": "77.117200",
                    "serialNumber": 82,
                    "station": "SUU"
                },
                {
                    "lattitude": "11.086800",
                    "longitude": "77.185900",
                    "serialNumber": 83,
                    "station": "SNO"
                },
                {
                    "lattitude": "11.118100",
                    "longitude": "77.266200",
                    "serialNumber": 84,
                    "station": "VNJ"
                },
                {
                    "lattitude": "11.109300",
                    "longitude": "77.341600",
                    "serialNumber": 85,
                    "station": "TUP"
                },
                {
                    "lattitude": "11.156200",
                    "longitude": "77.448300",
                    "serialNumber": 86,
                    "station": "UKL"
                },
                {
                    "lattitude": "11.195900",
                    "longitude": "77.522600",
                    "serialNumber": 87,
                    "station": "VZ"
                },
                {
                    "lattitude": "11.224900",
                    "longitude": "77.587200",
                    "serialNumber": 88,
                    "station": "IGR"
                },
                {
                    "lattitude": "11.253200",
                    "longitude": "77.628600",
                    "serialNumber": 89,
                    "station": "PY"
                },
                {
                    "lattitude": "11.293000",
                    "longitude": "77.682200",
                    "serialNumber": 90,
                    "station": "TPM"
                },
                {
                    "lattitude": "11.327400",
                    "longitude": "77.725600",
                    "serialNumber": 91,
                    "station": "ED"
                },
                {
                    "lattitude": "11.350700",
                    "longitude": "77.760700",
                    "serialNumber": 92,
                    "station": "CV"
                },
                {
                    "lattitude": "11.396700",
                    "longitude": "77.819800",
                    "serialNumber": 93,
                    "station": "ANU"
                },
                {
                    "lattitude": "11.445872",
                    "longitude": "77.870579",
                    "serialNumber": 94,
                    "station": "SGE"
                },
                {
                    "lattitude": "11.482500",
                    "longitude": "77.900100",
                    "serialNumber": 95,
                    "station": "MVPM"
                },
                {
                    "lattitude": "11.551000",
                    "longitude": "77.987300",
                    "serialNumber": 96,
                    "station": "DC"
                },
                {
                    "lattitude": "11.596700",
                    "longitude": "78.074300",
                    "serialNumber": 97,
                    "station": "VRPD"
                },
                {
                    "lattitude": "11.671276",
                    "longitude": "78.112965",
                    "serialNumber": 98,
                    "station": "SA"
                },
                {
                    "lattitude": "11.696323",
                    "longitude": "78.096356",
                    "serialNumber": 99,
                    "station": "MGSJ"
                },
                {
                    "lattitude": "11.738100",
                    "longitude": "78.045500",
                    "serialNumber": 100,
                    "station": "OML"
                },
                {
                    "lattitude": "11.790400",
                    "longitude": "78.026900",
                    "serialNumber": 101,
                    "station": "SMDT"
                },
                {
                    "lattitude": "11.830800",
                    "longitude": "78.027600",
                    "serialNumber": 102,
                    "station": "KVLR"
                },
                {
                    "lattitude": "11.931500",
                    "longitude": "78.070200",
                    "serialNumber": 103,
                    "station": "TPP"
                },
                {
                    "lattitude": "11.983700",
                    "longitude": "78.152500",
                    "serialNumber": 104,
                    "station": "MPC"
                },
                {
                    "lattitude": "12.039500",
                    "longitude": "78.118500",
                    "serialNumber": 105,
                    "station": "SZV"
                },
                {
                    "lattitude": "12.126100",
                    "longitude": "78.154200",
                    "serialNumber": 106,
                    "station": "DPJ"
                },
                {
                    "lattitude": "12.297000",
                    "longitude": "78.071700",
                    "serialNumber": 107,
                    "station": "PCV"
                },
                {
                    "lattitude": "12.388900",
                    "longitude": "78.017300",
                    "serialNumber": 108,
                    "station": "MZU"
                },
                {
                    "lattitude": "12.514400",
                    "longitude": "78.027000",
                    "serialNumber": 109,
                    "station": "RYC"
                },
                {
                    "lattitude": "12.568303",
                    "longitude": "77.906628",
                    "serialNumber": 110,
                    "station": "PRNT"
                },
                {
                    "lattitude": "12.615800",
                    "longitude": "77.865300",
                    "serialNumber": 111,
                    "station": "KMLM"
                },
                {
                    "lattitude": "12.717700",
                    "longitude": "77.823000",
                    "serialNumber": 112,
                    "station": "HSRA"
                },
                {
                    "lattitude": "12.719010",
                    "longitude": "77.766170",
                    "serialNumber": 113,
                    "station": "MNKH"
                },
                {
                    "lattitude": "12.723400",
                    "longitude": "77.710200",
                    "serialNumber": 114,
                    "station": "AEK"
                },
                {
                    "lattitude": "12.813140",
                    "longitude": "77.710934",
                    "serialNumber": 115,
                    "station": "HLE"
                },
                {
                    "lattitude": "12.907403",
                    "longitude": "77.705784",
                    "serialNumber": 116,
                    "station": "CRLM"
                },
                {
                    "lattitude": "12.936900",
                    "longitude": "77.707300",
                    "serialNumber": 117,
                    "station": "BLRR"
                },
                {
                    "lattitude": "",
                    "longitude": "",
                    "serialNumber": 118,
                    "station": "BPHI"
                },
                {
                    "lattitude": "13.005770",
                    "longitude": "77.628236",
                    "serialNumber": 119,
                    "station": "BAND"
                },
                {
                    "lattitude": "13.042400",
                    "longitude": "77.586200",
                    "serialNumber": 120,
                    "station": "HEB"
                },
                {
                    "lattitude": "13.043359",
                    "longitude": "77.562447",
                    "serialNumber": 121,
                    "station": "LOGH"
                },
                {
                    "lattitude": "",
                    "longitude": "",
                    "serialNumber": 122,
                    "station": "YPRA"
                },
                {
                    "lattitude": "13.023039",
                    "longitude": "77.551374",
                    "serialNumber": 123,
                    "station": "YPR"
                }
            ],
            "validFrom": "15-Feb-2025",
            "validTo": "31-Dec-2099"
        }
    },
    "rc": "200",
    "rd": "Success.",
    "rs": "S"
}